dlg_home_content/None.py
dlg_home_content/__init__.py
dlg_home_content/_nbdev.py
dlg_home_content/cocoeval.py
dlg_home_content/e2e_inference.py
dlg_home_content/image_generator.py
dlg_home_content/inference_pipeline.py
dlg_home_content/labelme2coco.py
dlg_home_content/perspective_correction.py
dlg_home_content/test_metrics.py
dlg_home_content/tv_brand_classification.py
dlg_home_content/tv_detection.py
dlg_home_content/utils.py
dlg_home_content/utils_parsing.py
dlg_home_content-0.0.8.dist-info/LICENSE
dlg_home_content-0.0.8.dist-info/METADATA
dlg_home_content-0.0.8.dist-info/WHEEL
dlg_home_content-0.0.8.dist-info/entry_points.txt
dlg_home_content-0.0.8.dist-info/top_level.txt
dlg_home_content-0.0.8.dist-info/RECORD
